{"credits":[{"name":"Kleber Andrade","email":"pdjkleber@gmail.com","jobs":"Game Designer and Lead Programmer","image":"kleber"},{"name":"Anderson Matheus","email":"matheusgentil@hotmail.com","jobs":"Composer and Sound Designer","image":"anderson"},{"name":"Carolina Damiani","email":"ma_carolina_@live.com","jobs":"Art, Character Designer and Animation","image":"carolina"},{"name":"Gabriel Quibao","email":"gquibao@gmail.com","jobs":"Art, Level Designer","image":"gabriel"},{"name":"Marcus Rocha","email":"marcusrochabae@hotmail.com","jobs":"Boy Programmer and Lead Gameplay Designer","image":"marcus"},{"name":"Vinicius Carli","email":"","jobs":"Art, Character Designer and Animation","image":"vinicius"},{"name":"Gabriel Bergamo","email":"","jobs":"UI Design and QA","image":"bergamo"}]}